viur_cli/__init__.py
viur_cli/build.py
viur_cli/cli.py
viur_cli/cloud.py
viur_cli/conf.py
viur_cli/deprecated.py
viur_cli/local.py
viur_cli/package.py
viur_cli/setup.py
viur_cli/tool.py
viur_cli/update.py
viur_cli/utils.py
viur_cli/version.py
viur_cli/scriptor/__init__.py
viur_cli/scriptor/cli.py
viur_cli/scripts/__init__.py
viur_cli/scripts/get_pyodide.py
viur_cli-2.3.1.dist-info/licenses/LICENSE
viur_cli-2.3.1.dist-info/METADATA
viur_cli-2.3.1.dist-info/WHEEL
viur_cli-2.3.1.dist-info/entry_points.txt
viur_cli-2.3.1.dist-info/top_level.txt
viur_cli-2.3.1.dist-info/RECORD
