Metadata-Version: 2.4
Name: viur-cli
Version: 2.3.1
Summary: Command-line interface for ViUR application maintenance.
Author-email: "Andreas H. Kelch" <ak@mausbrand.de>
License-Expression: MIT
Project-URL: Homepage, https://github.com/viur-framework/viur-cli
Project-URL: Bug Tracker, https://github.com/viur-framework/viur-cli/issues
Classifier: Programming Language :: Python :: 3
Classifier: Operating System :: OS Independent
Requires-Python: >=3.11
License-File: LICENSE
Requires-Dist: app-server~=1.0
Requires-Dist: click~=8.1.7
Requires-Dist: pipfile-requirements~=0.3
Requires-Dist: requests~=2.0
Requires-Dist: semver~=3.0
Requires-Dist: watchdog~=6.0
Requires-Dist: safety~=3.5
Requires-Dist: viur-scriptor-api~=1.0
Dynamic: license-file
